{
  "transfers": ["transfers": [
  {
    "symbol":"WETH",
    "amount":"135504631.82113272",
    "from":"Morpho",
    "to":""
  },
  {
    "symbol":"USDC",
    "amount":"3500000",
    "from":"",
    "to":""
  },
  {
    "symbol":"USDT",
    "amount":"2500000",
    "from":"",
    "to":"HTX"
  },
  {
    "symbol":"WETH",
    "amount":"1105943.898906035",
    "from":"Aerodrome Finance",
    "to":""
  },
  {
    "symbol":"WETH",
    "amount":"1105943.898906035",
    "from":"",
    "to":"Aerodrome Finance"
  }
],],
  "transfers_count": "0",
  "whale_score": "7/10",
  "analysis": "Whale Score: 7/10, نوع الحركة: تراكم, Fake Hunt: 25%, ماذا تفعل: فرصة, الخلاصة: سحب ضخم من بروتوكول مورفو بقيمة 135 مليون دولار إيثيريوم يشير لتحركات حيتان تراكمية مع معدل تمويل إيجابي",
  "prices": {
    "btc": {
      "price": "77049.98000000",
      "change": "0.535"
    },
    "eth": {
      "price": "2126.52000000",
      "change": "0.684"
    },
    "sol": {
      "price": "646.59000000",
      "change": "1.155"
    },
    "bnb": {
      "price": "85.70000000",
      "change": "1.528"
    }
  },
  "market": {
    "funding": "0.00006577",
    "oi": "10007.66",
    "count": "9233"
  }
}